{
    "collectionName": "components_hours_hours_of_operations",
    "info": {
      "name": "hours_of_operation",
      "icon": "calendar-alt"
    },
    "options": {},
    "attributes": {
      "closing_hours": {
        "type": "time",
        "default": "22:00:00"
      },
      "opening_hours": {
        "type": "time",
        "required": false,
        "default": "10:00:00"
      },
      "open_all_day": {
        "type": "boolean",
        "default": false,
        "required": true
      },
      "day_of_operation": {
        "type": "enumeration",
        "enum": [
          "Monday",
          "Tuesday",
          "Wednesday",
          "Thursday",
          "Friday",
          "Saturday",
          "Sunday"
        ],
        "required": true,
        "unique": false
      }
    }
  }